thalesians/__init__.py
thalesians/stochastics/__init__.py
thalesians/stochastics/distrs.py
thalesians/stochastics/kde.py
thalesians/stochastics/outliers.py
thalesians/stochastics/processes.py
thalesians/stochastics/simulation.py
thalesians/stochastics/filtering/__init__.py
thalesians/stochastics/filtering/kalman.py
thalesians/stochastics/filtering/particle.py
thalesians/stochastics/filtering/visual.py
thalesians.stochastics-0.0.1.dist-info/LICENSE
thalesians.stochastics-0.0.1.dist-info/METADATA
thalesians.stochastics-0.0.1.dist-info/WHEEL
thalesians.stochastics-0.0.1.dist-info/top_level.txt
thalesians.stochastics-0.0.1.dist-info/RECORD
