Metadata-Version: 2.1
Name: thalesians.stochastics
Version: 0.0.1
Summary: A special-purpose Python library for simulation, stochastic analysis, and stochastic filtering
Author-email: Paul Alexander Bilokon <paul@thalesians.com>, Abir Sridi <abir.sridi@thalesians.com>
Project-URL: Homepage, https://github.com/thalesians/stochastics/
Project-URL: Issues, https://github.com/thalesians/stochastics/issues
Classifier: Programming Language :: Python :: 3
Classifier: License :: OSI Approved :: Apache Software License
Classifier: Operating System :: OS Independent
Requires-Python: >=3.12
License-File: LICENSE
Requires-Dist: thalesians.adiutor>=0.0.3
Requires-Dist: numpy>=1.26.4
Requires-Dist: statsmodels>=0.14.4
Requires-Dist: matplotlib>=3.9.2
